airavata_django_portal_sdk/__init__.py
airavata_django_portal_sdk/apps.py
airavata_django_portal_sdk/decorators.py
airavata_django_portal_sdk/models.py
airavata_django_portal_sdk/queue_settings_calculators.py
airavata_django_portal_sdk/remoteapi.py
airavata_django_portal_sdk/serializers.py
airavata_django_portal_sdk/urls.py
airavata_django_portal_sdk/util.py
airavata_django_portal_sdk/views.py
airavata_django_portal_sdk/experiment_util/__init__.py
airavata_django_portal_sdk/experiment_util/api.py
airavata_django_portal_sdk/experiment_util/intermediate_output.py
airavata_django_portal_sdk/migrations/0001_initial.py
airavata_django_portal_sdk/migrations/0002_userfiles_file_resource_id.py
airavata_django_portal_sdk/migrations/0003_auto_20220225_1510.py
airavata_django_portal_sdk/migrations/__init__.py
airavata_django_portal_sdk/tests/__init__.py
airavata_django_portal_sdk/tests/test_queue_settings_calculator.py
airavata_django_portal_sdk/tests/test_settings.py
airavata_django_portal_sdk/tests/test_user_storage.py
airavata_django_portal_sdk/tests/test_util.py
airavata_django_portal_sdk/tests/test_views.py
airavata_django_portal_sdk/user_storage/__init__.py
airavata_django_portal_sdk/user_storage/api.py
airavata_django_portal_sdk/user_storage/backends/CredCommon_pb2.py
airavata_django_portal_sdk/user_storage/backends/CredCommon_pb2_grpc.py
airavata_django_portal_sdk/user_storage/backends/MFTApi_pb2.py
airavata_django_portal_sdk/user_storage/backends/MFTApi_pb2_grpc.py
airavata_django_portal_sdk/user_storage/backends/__init__.py
airavata_django_portal_sdk/user_storage/backends/base.py
airavata_django_portal_sdk/user_storage/backends/django_filesystem_provider.py
airavata_django_portal_sdk/user_storage/backends/mft_provider.py
airavata_django_portal_sdk-1.8.4.dist-info/LICENSE
airavata_django_portal_sdk-1.8.4.dist-info/METADATA
airavata_django_portal_sdk-1.8.4.dist-info/WHEEL
airavata_django_portal_sdk-1.8.4.dist-info/top_level.txt
airavata_django_portal_sdk-1.8.4.dist-info/RECORD
