Metadata-Version: 2.1
Name: airavata-django-portal-sdk
Version: 1.8.4
Summary: The Airavata Django Portal SDK is a library that makes it easier to develop Airavata Django Portal customizations.
Home-page: https://github.com/apache/airavata-django-portal-sdk
Author: Apache Software Foundation
Author-email: dev@airavata.apache.org
License: Apache License 2.0
Classifier: Development Status :: 4 - Beta
Classifier: Environment :: Web Environment
Classifier: Framework :: Django
Classifier: Intended Audience :: Developers
Classifier: License :: OSI Approved :: Apache Software License
Classifier: Natural Language :: English
Classifier: Programming Language :: Python :: 3.6
Classifier: Topic :: Internet :: WWW/HTTP
Classifier: Topic :: Internet :: WWW/HTTP :: WSGI :: Application
License-File: LICENSE
Requires-Dist: django
Requires-Dist: djangorestframework
Requires-Dist: airavata-python-sdk
Requires-Dist: requests (<2.28.0)
Requires-Dist: zipstream-new
